volkswagencarnet/__init__.py
volkswagencarnet/version.py
volkswagencarnet/vw_connection.py
volkswagencarnet/vw_const.py
volkswagencarnet/vw_dashboard.py
volkswagencarnet/vw_exceptions.py
volkswagencarnet/vw_utilities.py
volkswagencarnet/vw_vehicle.py
volkswagencarnet-5.4.5.dist-info/licenses/LICENSE.txt
volkswagencarnet-5.4.5.dist-info/METADATA
volkswagencarnet-5.4.5.dist-info/WHEEL
volkswagencarnet-5.4.5.dist-info/top_level.txt
volkswagencarnet-5.4.5.dist-info/RECORD
