Metadata-Version: 2.4
Name: volkswagencarnet
Version: 5.4.5
Summary: Communicate with Volkswagen Connect
Home-page: https://github.com/robinostlund/volkswagencarnet
Author: Robin Ostlund
Author-email: me@robinostlund.name
License: GPLv3
Project-URL: Bug Tracker, https://github.com/robinostlund/volkswagencarnet/issues
Classifier: Programming Language :: Python :: 3
Classifier: License :: OSI Approved :: GNU General Public License v3 (GPLv3)
Classifier: Operating System :: OS Independent
Requires-Python: >=3.11
License-File: LICENSE.txt
Requires-Dist: lxml
Requires-Dist: beautifulsoup4
Requires-Dist: aiohttp
Requires-Dist: pyjwt
Dynamic: license-file
